<?xml version="1.0" encoding="utf-8"?>
<song xmlns="http://21wdh.staszic.waw.pl" xmlns:xsi="http://www.w3.org/2001/XMLSchema-instance" xsi:schemaLocation="http://21wdh.staszic.waw.pl https://spiewaj.com/song.xsd" title="Piosenka dla Dośki">
  <comment/>
  <artist type="band">Dom o Zielonych Progach</artist>
  <lyric>
    <block type="verse">
      <row important_over="true">Jeszcze <ch a="G"/>noc, jeszcze <ch a="C"/>cienie się <ch a="G"/>chwieją<ch a="C"/></row>
      <row important_over="true">Cichym <ch a="G"/>snem <ch a="C"/>oddycha cały <ch a="e"/>dom<ch a="D"/></row>
      <row important_over="true">Moje <ch a="G"/>myśli <ch a="C"/>błądzą między <ch a="G"/>złudą a <ch a="C"/>nadzieją</row>
      <row important_over="true">A <ch a="G"/>czasami do snów <ch a="C"/>Twoich <ch a="D"/>zajrzeć <ch a="G"/>chcą</row>
    </block>
    <block type="chorus">
      <row important_over="true">To będ<ch a="C"/>zie do<ch a="D"/>bry dzień</row>
      <row important_over="true"><ch a="G"/>Jeśli rano mnie <ch a="C"/>przywitasz</row>
      <row important_over="true"><ch a="e"/>Ciepłych rąk dotknięciem</row>
      <row important_over="true"><ch a="A"/>Bez niepotrzebnych <ch a="D"/>słów</row>
      <row important_over="true">To będzie <ch a="C"/>dobry <ch a="D"/>dzień</row>
      <row important_over="true">Z Twojej <ch a="G"/>twarzy to <ch a="C"/>wyczytam</row>
      <row important_over="true">Dzień się <ch a="G"/>budzi, Ty się <ch a="C"/>budzisz</row>
      <row important_over="true"><ch a="D"/>Witaj <ch a="G"/>dniu</row>
    </block>
    <block type="verse">
      <row important_over="false">Jakie <ch a="G"/>imię chcesz <ch a="C"/>darować mu na <ch a="G"/>drogę<ch a="C"/></row>
      <row important_over="false">Jakim <ch a="G"/>słowem <ch a="C"/>przywita go nasz <ch a="e"/>dom<ch a="D"/></row>
      <row important_over="false">Czy gdy <ch a="G"/>jesień <ch a="C"/>przyjdzie będzie <ch a="G"/>jej za <ch a="C"/>osłodę</row>
      <row important_over="false">Wszak we <ch a="G"/>dwoje jesień <ch a="C"/>nie jest <ch a="D"/>porą <ch a="G"/>złą</row>
    </block>
    <blocklink blocknb="2"/>
  </lyric>
  <keywords/>
  <genre>Piosenka turystyczna</genre>
  <status>
    <done/>
    <verificators/>
  </status>
</song>
